[
    {
        "actionName": "UC01_Login",
        "steps": [
            {
                "stepId": "STEP753",
                "stepName": "Url: /",
                "infFile": "t1.inf",
                "time": 1575042792896
            },
            {
                "stepId": "STEP754",
                "stepName": "Url: /login",
                "infFile": "t2.inf",
                "time": 1575042793144
            },
            {
                "stepId": "STEP755",
                "stepName": "Url: {/",
                "infFile": "t4.inf",
                "time": 1575042793569
            },
            {
                "stepId": "STEP756",
                "stepName": "Url: /api/checkLogin",
                "infFile": "t5.inf",
                "time": 1575042793721
            },
            {
                "stepId": "STEP757",
                "stepName": "Url: /api/user/info",
                "infFile": "t6.inf",
                "time": 1575042793886
            },
            {
                "stepId": "STEP758",
                "stepName": "Url: /api/ticket/countByState/4",
                "infFile": "t7.inf",
                "time": 1575042794010
            },
            {
                "stepId": "STEP759",
                "stepName": "Url: /api/ticket/countByState/",
                "infFile": "t8.inf",
                "time": 1575042794164
            },
            {
                "stepId": "STEP760",
                "stepName": "Custom Request: /api/ticket/",
                "infFile": "t9.inf",
                "time": 1575042795627
            }
        ],
        "transactions": [
            {
                "transactionName": "UC01_TR01_Login",
                "rawStartTime": 1575042793149,
                "rawEndTime": 1575042795628,
                "thinkTime": 0.0,
                "wastedTime": 0.655583381652832
            }
        ]
    },
    {
        "actionName": "UC01_Create_incident",
        "steps": [
            {
                "stepId": "STEP761",
                "stepName": "Url: /api/user/catalog/node/0/children/",
                "infFile": "t10.inf",
                "time": 1575042795760
            },
            {
                "stepId": "STEP762",
                "stepName": "Url: /api/shops",
                "infFile": "t12.inf",
                "time": 1575042795931
            },
            {
                "stepId": "STEP763",
                "stepName": "Url: /api/shops",
                "infFile": "t13.inf",
                "time": 1575042796098
            },
            {
                "stepId": "STEP764",
                "stepName": "Url: /api/user/catalog/node/0/children/",
                "infFile": "t14.inf",
                "time": 1575042796256
            },
            {
                "stepId": "STEP765",
                "stepName": "Url: /api/user/catalog/treeview",
                "infFile": "t17.inf",
                "time": 1575042796861
            },
            {
                "stepId": "STEP766",
                "stepName": "Url: /api/user/catalog/node/146/children/",
                "infFile": "t18.inf",
                "time": 1575042797025
            },
            {
                "stepId": "STEP767",
                "stepName": "Url: /api/user/catalog/node/146/service/",
                "infFile": "t19.inf",
                "time": 1575042797187
            },
            {
                "stepId": "STEP768",
                "stepName": "Url: }/api/user/catalog/breadcrumbs/146",
                "infFile": "t20.inf",
                "time": 1575042797341
            },
            {
                "stepId": "STEP769",
                "stepName": "Url: /api/inventoryNumbers",
                "infFile": "t22.inf",
                "time": 1575042797507
            },
            {
                "stepId": "STEP770",
                "stepName": "Url: /api/inventoryNumbers",
                "infFile": "t23.inf",
                "time": 1575042797670
            },
            {
                "stepId": "STEP771",
                "stepName": "Custom Request: /api/ticket/",
                "infFile": "t24.inf",
                "time": 1575042797967
            },
            {
                "stepId": "STEP772",
                "stepName": "Url: /",
                "infFile": "t25.inf",
                "time": 1575042798071
            },
            {
                "stepId": "STEP773",
                "stepName": "Url: /api/checkLogin",
                "infFile": "t26.inf",
                "time": 1575042798224
            },
            {
                "stepId": "STEP774",
                "stepName": "Url: /api/user/info",
                "infFile": "t27.inf",
                "time": 1575042798380
            },
            {
                "stepId": "STEP775",
                "stepName": "Url: /api/ticket/countByState/4",
                "infFile": "t28.inf",
                "time": 1575042798498
            },
            {
                "stepId": "STEP776",
                "stepName": "Url: /api/ticket/countByState/",
                "infFile": "t29.inf",
                "time": 1575042798620
            },
            {
                "stepId": "STEP777",
                "stepName": "Url: /api/ticket/countByState/",
                "infFile": "t30.inf",
                "time": 1575042798779
            },
            {
                "stepId": "STEP778",
                "stepName": "Custom Request: /api/ticket",
                "infFile": "t31.inf",
                "time": 1575042799830
            },
            {
                "stepId": "STEP779",
                "stepName": "Custom Request: /api/ticket",
                "infFile": "t32.inf",
                "time": 1575042800895
            }
        ],
        "transactions": [
            {
                "transactionName": "UC01_TR02_Create_incident",
                "rawStartTime": 1575042795640,
                "rawEndTime": 1575042795761,
                "thinkTime": 0.0,
                "wastedTime": 0.08943414688110352
            },
            {
                "transactionName": "UC01_TR03_Incident_data",
                "rawStartTime": 1575042795765,
                "rawEndTime": 1575042800897,
                "thinkTime": 0.0,
                "wastedTime": 1.760218858718872
            }
        ]
    },
    {
        "actionName": "UC01_Logout",
        "steps": [
            {
                "stepId": "STEP780",
                "stepName": "Url: /api/logout",
                "infFile": "t33.inf",
                "time": 1575042801048
            },
            {
                "stepId": "STEP781",
                "stepName": "Url: /login",
                "infFile": "t34.inf",
                "time": 1575042801178
            }
        ],
        "transactions": [
            {
                "transactionName": "UC01_TR04_Logout",
                "rawStartTime": 1575042800909,
                "rawEndTime": 1575042801179,
                "thinkTime": 0.0,
                "wastedTime": 0.1962752342224121
            }
        ]
    }
]