[
    {
        "actionName": "UC01_Login",
        "steps": [
            {
                "stepId": "STEP232",
                "stepName": "Url: /",
                "infFile": "t1.inf",
                "time": 1575042658242
            },
            {
                "stepId": "STEP233",
                "stepName": "Url: /login",
                "infFile": "t2.inf",
                "time": 1575042658431
            },
            {
                "stepId": "STEP234",
                "stepName": "Url: {/",
                "infFile": "t4.inf",
                "time": 1575042658684
            },
            {
                "stepId": "STEP235",
                "stepName": "Url: /api/checkLogin",
                "infFile": "t5.inf",
                "time": 1575042658790
            },
            {
                "stepId": "STEP236",
                "stepName": "Url: /api/user/info",
                "infFile": "t6.inf",
                "time": 1575042658892
            },
            {
                "stepId": "STEP237",
                "stepName": "Url: /api/ticket/countByState/4",
                "infFile": "t7.inf",
                "time": 1575042658952
            },
            {
                "stepId": "STEP238",
                "stepName": "Url: /api/ticket/countByState/",
                "infFile": "t8.inf",
                "time": 1575042659014
            },
            {
                "stepId": "STEP239",
                "stepName": "Custom Request: /api/ticket/",
                "infFile": "t9.inf",
                "time": 1575042660008
            }
        ],
        "transactions": [
            {
                "transactionName": "UC01_TR01_Login",
                "rawStartTime": 1575042658436,
                "rawEndTime": 1575042660010,
                "thinkTime": 0.0,
                "wastedTime": 0.242142915725708
            }
        ]
    },
    {
        "actionName": "UC01_Create_incident",
        "steps": [
            {
                "stepId": "STEP240",
                "stepName": "Url: /api/user/catalog/node/0/children/",
                "infFile": "t10.inf",
                "time": 1575042660113
            },
            {
                "stepId": "STEP241",
                "stepName": "Url: /api/shops",
                "infFile": "t12.inf",
                "time": 1575042660222
            },
            {
                "stepId": "STEP242",
                "stepName": "Url: /api/shops",
                "infFile": "t13.inf",
                "time": 1575042660325
            },
            {
                "stepId": "STEP243",
                "stepName": "Url: /api/user/catalog/node/0/children/",
                "infFile": "t14.inf",
                "time": 1575042660424
            },
            {
                "stepId": "STEP244",
                "stepName": "Url: /api/user/catalog/treeview",
                "infFile": "t17.inf",
                "time": 1575042660752
            },
            {
                "stepId": "STEP245",
                "stepName": "Url: /api/user/catalog/node/146/children/",
                "infFile": "t18.inf",
                "time": 1575042660855
            },
            {
                "stepId": "STEP246",
                "stepName": "Url: /api/user/catalog/node/146/service/",
                "infFile": "t19.inf",
                "time": 1575042660922
            },
            {
                "stepId": "STEP247",
                "stepName": "Url: }/api/user/catalog/breadcrumbs/146",
                "infFile": "t20.inf",
                "time": 1575042661019
            },
            {
                "stepId": "STEP248",
                "stepName": "Url: /api/inventoryNumbers",
                "infFile": "t22.inf",
                "time": 1575042661119
            },
            {
                "stepId": "STEP249",
                "stepName": "Url: /api/inventoryNumbers",
                "infFile": "t23.inf",
                "time": 1575042661213
            },
            {
                "stepId": "STEP250",
                "stepName": "Custom Request: /api/ticket/",
                "infFile": "t24.inf",
                "time": 1575042661343
            }
        ],
        "transactions": [
            {
                "transactionName": "UC01_TR02_Create_incident",
                "rawStartTime": 1575042660021,
                "rawEndTime": 1575042660115,
                "thinkTime": 0.0,
                "wastedTime": 0.033142805099487308
            },
            {
                "transactionName": "UC01_TR03_Incident_data",
                "rawStartTime": 1575042660119,
                "rawEndTime": 1575042661343,
                "thinkTime": 0.0,
                "wastedTime": 0.38468265533447268
            }
        ]
    }
]